README.md
setup.cfg
setup.py
instagram/__init__.py
instagram/bind.py
instagram/client.py
instagram/helper.py
instagram/json_import.py
instagram/models.py
instagram/oauth2.py
instagram/subscriptions.py
python_instagram_ext.egg-info/PKG-INFO
python_instagram_ext.egg-info/SOURCES.txt
python_instagram_ext.egg-info/dependency_links.txt
python_instagram_ext.egg-info/requires.txt
python_instagram_ext.egg-info/top_level.txt
python_instagram_ext.egg-info/zip-safe