Metadata-Version: 1.0
Name: python-instagram-ext
Version: 1.3.10
Summary: Life extended Instagram API client
Home-page: https://github.com/Seraphicer/python-instagram-ext.git
Author: Seraphicer
Author-email: tomoyuki.kakuda@gmail.com
License: MIT
Keywords: instagram
Platform: UNKNOWN
